setup.py
salure_helpers/brynq/__init__.py
salure_helpers/brynq/brynq.py
salure_helpers_brynq.egg-info/PKG-INFO
salure_helpers_brynq.egg-info/SOURCES.txt
salure_helpers_brynq.egg-info/dependency_links.txt
salure_helpers_brynq.egg-info/not-zip-safe
salure_helpers_brynq.egg-info/requires.txt
salure_helpers_brynq.egg-info/top_level.txt