Metadata-Version: 1.0
Name: salure-helpers-brynq
Version: 2.0.0
Summary: Brynq Python SDK
Home-page: UNKNOWN
Author: D&A Salure
Author-email: support@brynq.com
License: Brynq License
Platform: UNKNOWN
